fivem/__init__.py
fivem/fivem.py
fivem/player.py
fivem/server.py
fivem_api-0.1.2.dist-info/LICENSE
fivem_api-0.1.2.dist-info/METADATA
fivem_api-0.1.2.dist-info/WHEEL
fivem_api-0.1.2.dist-info/top_level.txt
fivem_api-0.1.2.dist-info/RECORD
